youtube_html_parser/__init__.py
youtube_html_parser/base.py
youtube_html_parser/cli.py
youtube_html_parser/parser.py
youtube_html_parser/run.py
youtube_html_parser/web.py
youtube_html_parser/ytdlp.py
youtube_html_parser/ytpage.py
youtube_html_parser/ytpagesearch.py
youtube_html_parser/assets/example.txt
youtube_html_parser-1.0.2.dist-info/LICENSE
youtube_html_parser-1.0.2.dist-info/METADATA
youtube_html_parser-1.0.2.dist-info/WHEEL
youtube_html_parser-1.0.2.dist-info/entry_points.txt
youtube_html_parser-1.0.2.dist-info/top_level.txt
youtube_html_parser-1.0.2.dist-info/RECORD
